{
    "characters": [
        {
            "name": "ㄱ",
            "kind": ["son"],
            "path": [
                {"start": [0.0, 0.0, 0.2], "end": [0.0, 0.2, 0.2]},
                {"start": [0.0, 0.2, 0.2], "end": [0.0, 0.2, 0.0]}
            ]
        },
        {
            "name": "ㄲ",
            "kind": ["son"],
            "path": [
                {"start": [0.0, 0.0, 0.2], "end": [0.0, 0.1, 0.2]},
                {"start": [0.0, 0.1, 0.2], "end": [0.0, 0.1, 0.0]},
                {"start": [0.0, 0.1, 0.2], "end": [0.0, 0.2, 0.2]},
                {"start": [0.0, 0.2, 0.2], "end": [0.0, 0.2, 0.0]}
            ]
        },
        {
            "name": "ㄴ",
            "kind": ["son"],
            "path": [
                {"start": [0.0, 0.0, 0.2], "end": [0.0, 0.0, 0.0]},
                {"start": [0.0, 0.0, 0.0], "end": [0.0, 0.2, 0.0]}
            ]
        },
        {
            "name": "ㄷ",
            "kind": ["son"],
            "path": [
                {"start": [0.0, 0.0, 0.2], "end": [0.0, 0.2, 0.2]},
                {"start": [0.0, 0.0, 0.2], "end": [0.0, 0.0, 0.0]},
                {"start": [0.0, 0.0, 0.0], "end": [0.0, 0.2, 0.0]}
            ]
        },
        {
            "name": "ㄸ",
            "kind": ["son"],
            "path": [
                {"start": [0.0, 0.0, 0.2], "end": [0.0, 0.1, 0.2]},
                {"start": [0.0, 0.1, 0.2], "end": [-0.5, 0.1, 0.2]},
                {"start": [-0.5, 0.1, 0.2], "end": [-0.5, 0.0, 0.2]},
                {"start": [0.0, 0.0, 0.2], "end": [0.0, 0.0, 0.0]},
                {"start": [0.0, 0.0, 0.0], "end": [0.0, 0.1, 0.0]},
                {"start": [0.0, 0.1, 0.0], "end": [-0.5, 0.1, 0.0]},
                {"start": [-0.5, 0.1, 0.0], "end": [0.0, 0.1, 0.2]},
                {"start": [0.0, 0.1, 0.2], "end": [0.0, 0.2, 0.2]},
                {"start": [0.0, 0.2, 0.2], "end": [-0.5, 0.2, 0.2]},
                {"start": [-0.5, 0.2, 0.2], "end": [0.0, 0.1, 0.2]},
                {"start": [0.0, 0.1, 0.2], "end": [0.0, 0.1, 0.0]},
                {"start": [0.0, 0.1, 0.0], "end": [0.0, 0.2, 0.0]}
            ]
        },
        {
            "name": "ㄹ",
            "kind": ["son"],
            "path": [
                {"start": [0.0, 0.0, 0.2], "end": [0.0, 0.2, 0.2]},
                {"start": [0.0, 0.2, 0.2], "end": [0.0, 0.2, 0.1]},
                {"start": [0.0, 0.0, 0.1], "end": [0.0, 0.2, 0.1]},
                {"start": [0.0, 0.0, 0.1], "end": [0.0, 0.0, 0.0]},
                {"start": [0.0, 0.0, 0.0], "end": [0.0, 0.2, 0.0]}
            ]
        },
        {
            "name": "ㅁ",
            "kind": ["son"],
            "path": [
                {"start": [0.0, 0.0, 0.2], "end": [0.0, 0.0, 0.0]},
                {"start": [0.0, 0.0, 0.2], "end": [0.0, 0.2, 0.2]},
                {"start": [0.0, 0.2, 0.2], "end": [0.0, 0.2, 0.0]},
                {"start": [0.0, 0.0, 0.0], "end": [0.0, 0.2, 0.0]}
            ]
        },
        {
            "name": "ㅂ",
            "kind": ["son"],
            "path": [
                {"start": [0.0, 0.0, 0.2], "end": [0.0, 0.0, 0.0]},
                {"start": [0.0, 0.2, 0.2], "end": [0.0, 0.2, 0.0]},
                {"start": [0.0, 0.0, 0.1], "end": [0.0, 0.2, 0.1]},
                {"start": [0.0, 0.0, 0.0], "end": [0.0, 0.2, 0.0]}
            ]
        },
        {
            "name": "ㅃ",
            "kind": ["son"],
            "path": [
                {"start": [0.0, 0.0, 0.2], "end": [0.0, 0.0, 0.0]},
                {"start": [0.0, 0.09, 0.2], "end": [0.0, 0.09, 0.0]},
                {"start": [0.0, 0.0, 0.1], "end": [0.0, 0.09, 0.1]},
                {"start": [0.0, 0.0, 0.0], "end": [0.0, 0.09, 0.0]},
                {"start": [0.0, 0.11, 0.2], "end": [0.0, 0.11, 0.0]},
                {"start": [0.0, 0.2, 0.2], "end": [0.0, 0.2, 0.0]},
                {"start": [0.0, 0.11, 0.1], "end": [0.0, 0.2, 0.1]},
                {"start": [0.0, 0.11, 0.0], "end": [0.0, 0.2, 0.0]}
            ]
        },
        {
            "name": "ㅅ",
            "kind": ["son"],
            "path": [
                {"start": [0.0, 0.12, 0.2], "end": [0.0, 0.0, 0.0]},
                {"start": [0.0, 0.11, 0.17], "end": [0.0, 0.2, 0.0]}
            ]
        },
        {
            "name": "ㅆ",
            "kind": ["son"],
            "path": [
                {"start": [0.0, 0.06, 0.2], "end": [0.0, 0.0, 0.0]},
                {"start": [0.0, 0.055, 0.17], "end": [0.0, 0.1, 0.0]},
                {"start": [0.0, 0.16, 0.2], "end": [0.0, 0.1, 0.0]},
                {"start": [0.0, 0.155, 0.17], "end": [0.0, 0.2, 0.0]}
            ]
        },
        {
            "name": "ㅇ",
            "kind": ["son"],
            "path": [
                {"start": [0.0, 0.1, 0.2], "end": [0.0, 0.075, 0.197]},
                {"start": [0.0, 0.075, 0.197], "end": [0.0, 0.05, 0.187]},
                {"start": [0.0, 0.05, 0.187], "end": [0.0, 0.025, 0.166]},
                {"start": [0.0, 0.025, 0.166], "end": [0.0, 0.0, 0.1]},
                {"start": [0.0, 0.0, 0.1], "end": [0.0, 0.025, 0.034]},
                {"start": [0.0, 0.025, 0.034], "end": [0.0, 0.05, 0.013]},
                {"start": [0.0, 0.05, 0.013], "end": [0.0, 0.075, 0.003]},
                {"start": [0.0, 0.075, 0.003], "end": [0.0, 0.1, 0.0]},
                {"start": [0.0, 0.1, 0.0], "end": [0.0, 0.125, 0.003]},
                {"start": [0.0, 0.125, 0.003], "end": [0.0, 0.15, 0.013]},
                {"start": [0.0, 0.15, 0.013], "end": [0.0, 0.175, 0.034]},
                {"start": [0.0, 0.175, 0.034], "end": [0.0, 0.2, 0.1]},
                {"start": [0.0, 0.2, 0.1], "end": [0.0, 0.175, 0.166]},
                {"start": [0.0, 0.175, 0.166], "end": [0.0, 0.15, 0.187]},
                {"start": [0.0, 0.15, 0.187], "end": [0.0, 0.125, 0.197]},
                {"start": [0.0, 0.125, 0.197], "end": [0.0, 0.1, 0.2]},
                {"start": [0.0, 0.1, 0.2], "end": [0.0, 0.075, 0.197]},
                {"start": [0.0, 0.075, 0.197], "end": [0.0, 0.05, 0.187]},
                {"start": [0.0, 0.05, 0.187], "end": [0.0, 0.025, 0.166]}
            ]
        },
        {
            "name": "ㅈ",
            "kind": ["son"],
            "path": [
                {"start": [0.0, 0.0, 0.2], "end": [0.0, 0.2, 0.2]},
                {"start": [0.0, 0.1, 0.2], "end": [0.0, 0.0, 0.0]},
                {"start": [0.0, 0.1, 0.2], "end": [0.0, 0.2, 0.0]}
            ]
        },
        {
            "name": "ㅉ",
            "kind": ["son"],
            "path": [
                {"start": [0.0, 0.0, 0.2], "end": [0.0, 0.1, 0.2]},
                {"start": [0.0, 0.05, 0.2], "end": [0.0, 0.0, 0.0]},
                {"start": [0.0, 0.05, 0.2], "end": [0.0, 0.1, 0.0]},
                {"start": [0.0, 0.1, 0.2], "end": [0.0, 0.2, 0.2]},
                {"start": [0.0, 0.15, 0.2], "end": [0.0, 0.1, 0.0]},
                {"start": [0.0, 0.15, 0.2], "end": [0.0, 0.2, 0.0]}
            ]
        },
        {
            "name": "ㅊ",
            "kind": ["son"],
            "path": [
                {"start": [0.0, 0.1, 0.2], "end": [0.0, 0.1, 0.13]},
                {"start": [0.0, 0.0, 0.13], "end": [0.0, 0.2, 0.13]},
                {"start": [0.0, 0.1, 0.13], "end": [0.0, 0.0, 0.0]},
                {"start": [0.0, 0.1, 0.13], "end": [0.0, 0.2, 0.0]}
            ]
        },
        {
            "name": "ㅋ",
            "kind": ["son"],
            "path": [
                {"start": [0.0, 0.0, 0.2], "end": [0.0, 0.2, 0.2]},
                {"start": [0.0, 0.2, 0.2], "end": [0.0, 0.2, 0.0]},
                {"start": [0.0, 0.0, 0.1], "end": [0.0, 0.2, 0.1]}
            ]
        },
        {
            "name": "ㅌ",
            "kind": ["son"],
            "path": [
                {"start": [0.0, 0.0, 0.2], "end": [0.0, 0.2, 0.2]},
                {"start": [0.0, 0.0, 0.1], "end": [0.0, 0.2, 0.1]},
                {"start": [0.0, 0.0, 0.2], "end": [0.0, 0.0, 0.0]},
                {"start": [0.0, 0.0, 0.0], "end": [0.0, 0.2, 0.0]}
            ]
        },
        {
            "name": "ㅍ",
            "kind": ["son"],
            "path": [
                {"start": [0.0, 0.0, 0.2], "end": [0.0, 0.2, 0.2]},
                {"start": [0.0, 0.05, 0.2], "end": [0.0, 0.05, 0.0]},
                {"start": [0.0, 0.15, 0.2], "end": [0.0, 0.15, 0.0]},
                {"start": [0.0, 0.0, 0.0], "end": [0.0, 0.2, 0.0]}
            ]
        },
        {
            "name": "ㅎ",
            "kind": ["son"],
            "path": [
                {"start": [0.0, 0.1, 0.2], "end": [0.0, 0.1, 0.13]},
                {"start": [0.0, 0.0, 0.13], "end": [0.0, 0.2, 0.13]},
                {"start": [0.0, 0.1, 0.12], "end": [0.0, 0.095, 0.1182]},
                {"start": [0.0, 0.095, 0.1182], "end": [0.0, 0.07, 0.1122]},
                {"start": [0.0, 0.07, 0.1122], "end": [0.0, 0.055, 0.0996]},
                {"start": [0.0, 0.055, 0.0996], "end": [0.0, 0.04, 0.06]},
                {"start": [0.0, 0.04, 0.06], "end": [0.0, 0.055, 0.0204]},
                {"start": [0.0, 0.055, 0.0204], "end": [0.0, 0.07, 0.0078]},
                {"start": [0.0, 0.07, 0.0078], "end": [0.0, 0.067, 0.0018]},
                {"start": [0.0, 0.067, 0.0018], "end": [0.0, 0.1, 0.0]},
                {"start": [0.0, 0.1, 0.0], "end": [0.0, 0.115, 0.0018]},
                {"start": [0.0, 0.115, 0.0018], "end": [0.0, 0.13, 0.0078]},
                {"start": [0.0, 0.13, 0.0078], "end": [0.0, 0.145, 0.0204]},
                {"start": [0.0, 0.145, 0.0204], "end": [0.0, 0.16, 0.06]},
                {"start": [0.0, 0.16, 0.06], "end": [0.0, 0.145, 0.0996]},
                {"start": [0.0, 0.145, 0.0996], "end": [0.0, 0.13, 0.1122]},
                {"start": [0.0, 0.13, 0.1122], "end": [0.0, 0.115, 0.1182]},
                {"start": [0.0, 0.115, 0.1182], "end": [0.0, 0.1, 0.12]},
                {"start": [0.0, 0.1, 0.12], "end": [0.0, 0.095, 0.1182]},
                {"start": [0.0, 0.095, 0.1182], "end": [0.0, 0.07, 0.1122]},
                {"start": [0.0, 0.07, 0.1122], "end": [0.0, 0.055, 0.0996]}
            ]
        },
        {
            "name": "ㄳ",
            "kind": ["son"],
            "path": [
                {"start": [0.0, 0.0, 0.2], "end": [0.0, 0.09, 0.2]},
                {"start": [0.0, 0.09, 0.2], "end": [0.0, 0.09, 0.0]},
                {"start": [0.0, 0.16, 0.2], "end": [0.0, 0.1, 0.0]},
                {"start": [0.0, 0.155, 0.17], "end": [0.0, 0.2, 0.0]}
            ]
        },
        {
            "name": "ㄵ",
            "kind": ["son"],
            "path": [
                {"start": [0.0, 0.0, 0.2], "end": [0.0, 0.0, 0.0]},
                {"start": [0.0, 0.0, 0.0], "end": [0.0, 0.09, 0.0]},
                {"start": [0.0, 0.1, 0.2], "end": [0.0, 0.2, 0.2]},
                {"start": [0.0, 0.15, 0.2], "end": [0.0, 0.1, 0.0]},
                {"start": [0.0, 0.15, 0.2], "end": [0.0, 0.2, 0.0]}
            ]
        },
        {
            "name": "ㄶ",
            "kind": ["son"],
            "path": [
                {"start": [0.0, 0.0, 0.2], "end": [0.0, 0.0, 0.0]},
                {"start": [0.0, 0.0, 0.0], "end": [0.0, 0.09, 0.0]},
                {"start": [0.0, 0.15, 0.2], "end": [0.0, 0.15, 0.13]},
                {"start": [0.0, 0.1, 0.13], "end": [0.0, 0.2, 0.13]},
                {"start": [0.0, 0.15, 0.12], "end": [0.0, 0.1475, 0.1182]},
                {"start": [0.0, 0.1475, 0.1182], "end": [0.0, 0.135, 0.1122]},
                {"start": [0.0, 0.135, 0.1122], "end": [0.0, 0.1275, 0.0996]},
                {"start": [0.0, 0.1275, 0.0996], "end": [0.0, 0.12, 0.06]},
                {"start": [0.0, 0.12, 0.06], "end": [0.0, 0.1275, 0.0204]},
                {"start": [0.0, 0.1275, 0.0204], "end": [0.0, 0.135, 0.0078]},
                {"start": [0.0, 0.135, 0.0078], "end": [0.0, 0.1335, 0.0018]},
                {"start": [0.0, 0.1335, 0.0018], "end": [0.0, 0.15, 0.0]},
                {"start": [0.0, 0.15, 0.0], "end": [0.0, 0.1575, 0.0018]},
                {"start": [0.0, 0.1575, 0.0018], "end": [0.0, 0.165, 0.0078]},
                {"start": [0.0, 0.165, 0.0078], "end": [0.0, 0.1725, 0.0204]},
                {"start": [0.0, 0.1725, 0.0204], "end": [0.0, 0.18, 0.06]},
                {"start": [0.0, 0.18, 0.06], "end": [0.0, 0.1725, 0.0996]},
                {"start": [0.0, 0.1725, 0.0996], "end": [0.0, 0.165, 0.1122]},
                {"start": [0.0, 0.165, 0.1122], "end": [0.0, 0.1575, 0.1182]},
                {"start": [0.0, 0.1575, 0.1182], "end": [0.0, 0.15, 0.2]},
                {"start": [0.0, 0.15, 0.12], "end": [0.0, 0.1475, 0.1182]},
                {"start": [0.0, 0.1475, 0.1182], "end": [0.0, 0.135, 0.1122]},
                {"start": [0.0, 0.135, 0.1122], "end": [0.0, 0.1275, 0.0996]}
            ]
        },
        {
            "name": "ㄺ",
            "kind": ["son"],
            "path": [
                {"start": [0.0, 0.0, 0.2], "end": [0.0, 0.09, 0.2]},
                {"start": [0.0, 0.09, 0.2], "end": [0.0, 0.09, 0.1]},
                {"start": [0.0, 0.0, 0.1], "end": [0.0, 0.09, 0.1]},
                {"start": [0.0, 0.0, 0.1], "end": [0.0, 0.0, 0.0]},
                {"start": [0.0, 0.0, 0.0], "end": [0.0, 0.09, 0.0]},
                {"start": [0.0, 0.1, 0.2], "end": [0.0, 0.2, 0.2]},
                {"start": [0.0, 0.2, 0.2], "end": [0.0, 0.2, 0.0]}
            ]
        },
        {
            "name": "ㄻ",
            "kind": ["son"],
            "path": [
                {"start": [0.0, 0.0, 0.2], "end": [0.0, 0.09, 0.2]},
                {"start": [0.0, 0.09, 0.2], "end": [0.0, 0.09, 0.1]},
                {"start": [0.0, 0.0, 0.1], "end": [0.0, 0.09, 0.1]},
                {"start": [0.0, 0.0, 0.1], "end": [0.0, 0.0, 0.0]},
                {"start": [0.0, 0.0, 0.0], "end": [0.0, 0.09, 0.0]},
                {"start": [0.0, 0.11, 0.2], "end": [0.0, 0.11, 0.0]},
                {"start": [0.0, 0.11, 0.2], "end": [0.0, 0.2, 0.2]},
                {"start": [0.0, 0.2, 0.2], "end": [0.0, 0.2, 0.0]},
                {"start": [0.0, 0.11, 0.0], "end": [0.0, 0.2, 0.0]}
            ]
        },
        {
            "name": "ㄼ",
            "kind": ["son"],
            "path": [
                {"start": [0.0, 0.0, 0.2], "end": [0.0, 0.09, 0.2]},
                {"start": [0.0, 0.09, 0.2], "end": [0.0, 0.09, 0.1]},
                {"start": [0.0, 0.0, 0.1], "end": [0.0, 0.09, 0.1]},
                {"start": [0.0, 0.0, 0.1], "end": [0.0, 0.0, 0.0]},
                {"start": [0.0, 0.0, 0.0], "end": [0.0, 0.09, 0.0]},
                {"start": [0.0, 0.11, 0.2], "end": [0.0, 0.11, 0.0]},
                {"start": [0.0, 0.2, 0.2], "end": [0.0, 0.2, 0.0]},
                {"start": [0.0, 0.11, 0.1], "end": [0.0, 0.2, 0.1]},
                {"start": [0.0, 0.11, 0.0], "end": [0.0, 0.2, 0.0]}
            ]
        },
        {
            "name": "ㄽ",
            "kind": ["son"],
            "path": [
                {"start": [0.0, 0.0, 0.2], "end": [0.0, 0.09, 0.2]},
                {"start": [0.0, 0.09, 0.2], "end": [0.0, 0.09, 0.1]},
                {"start": [0.0, 0.0, 0.1], "end": [0.0, 0.09, 0.1]},
                {"start": [0.0, 0.0, 0.1], "end": [0.0, 0.0, 0.0]},
                {"start": [0.0, 0.0, 0.0], "end": [0.0, 0.09, 0.0]},
                {"start": [0.0, 0.16, 0.2], "end": [0.0, 0.1, 0.0]},
                {"start": [0.0, 0.155, 0.17], "end": [0.0, 0.2, 0.0]}
            ]
        },
        {
            "name": "ㄾ",
            "kind": ["son"],
            "path": [
                {"start": [0.0, 0.0, 0.2], "end": [0.0, 0.09, 0.2]},
                {"start": [0.0, 0.09, 0.2], "end": [0.0, 0.09, 0.1]},
                {"start": [0.0, 0.0, 0.1], "end": [0.0, 0.09, 0.1]},
                {"start": [0.0, 0.0, 0.1], "end": [0.0, 0.0, 0.0]},
                {"start": [0.0, 0.0, 0.0], "end": [0.0, 0.09, 0.0]},
                {"start": [0.0, 0.11, 0.2], "end": [0.0, 0.2, 0.2]},
                {"start": [0.0, 0.11, 0.1], "end": [0.0, 0.2, 0.1]},
                {"start": [0.0, 0.11, 0.2], "end": [0.0, 0.11, 0.0]},
                {"start": [0.0, 0.11, 0.0], "end": [0.0, 0.2, 0.0]}
            ]
        },
        {
            "name": "ㄿ",
            "kind": ["son"],
            "path": [
                {"start": [0.0, 0.0, 0.2], "end": [0.0, 0.09, 0.2]},
                {"start": [0.0, 0.09, 0.2], "end": [0.0, 0.09, 0.1]},
                {"start": [0.0, 0.0, 0.1], "end": [0.0, 0.09, 0.1]},
                {"start": [0.0, 0.0, 0.1], "end": [0.0, 0.0, 0.0]},
                {"start": [0.0, 0.0, 0.0], "end": [0.0, 0.09, 0.0]},
                {"start": [0.0, 0.1, 0.2], "end": [0.0, 0.2, 0.2]},
                {"start": [0.0, 0.125, 0.2], "end": [0.0, 0.125, 0.0]},
                {"start": [0.0, 0.175, 0.2], "end": [0.0, 0.175, 0.0]},
                {"start": [0.0, 0.1, 0.0], "end": [0.0, 0.2, 0.0]}
            ]
        },
        {
            "name": "ㅀ",
            "kind": ["son"],
            "path": [
                {"start": [0.0, 0.0, 0.2], "end": [0.0, 0.09, 0.2]},
                {"start": [0.0, 0.09, 0.2], "end": [0.0, 0.09, 0.1]},
                {"start": [0.0, 0.0, 0.1], "end": [0.0, 0.09, 0.1]},
                {"start": [0.0, 0.0, 0.1], "end": [0.0, 0.0, 0.0]},
                {"start": [0.0, 0.0, 0.0], "end": [0.0, 0.09, 0.0]},
                {"start": [0.0, 0.15, 0.2], "end": [0.0, 0.15, 0.13]},
                {"start": [0.0, 0.1, 0.13], "end": [0.0, 0.2, 0.13]},
                {"start": [0.0, 0.15, 0.12], "end": [0.0, 0.1475, 0.1182]},
                {"start": [0.0, 0.1475, 0.1182], "end": [0.0, 0.135, 0.1122]},
                {"start": [0.0, 0.135, 0.1122], "end": [0.0, 0.1275, 0.0996]},
                {"start": [0.0, 0.1275, 0.0996], "end": [0.0, 0.12, 0.06]},
                {"start": [0.0, 0.12, 0.06], "end": [0.0, 0.1275, 0.0204]},
                {"start": [0.0, 0.1275, 0.0204], "end": [0.0, 0.135, 0.0078]},
                {"start": [0.0, 0.135, 0.0078], "end": [0.0, 0.1335, 0.0018]},
                {"start": [0.0, 0.1335, 0.0018], "end": [0.0, 0.15, 0.0]},
                {"start": [0.0, 0.15, 0.0], "end": [0.0, 0.1575, 0.0018]},
                {"start": [0.0, 0.1575, 0.0018], "end": [0.0, 0.165, 0.0078]},
                {"start": [0.0, 0.165, 0.0078], "end": [0.0, 0.1725, 0.0204]},
                {"start": [0.0, 0.1725, 0.0204], "end": [0.0, 0.18, 0.06]},
                {"start": [0.0, 0.18, 0.06], "end": [0.0, 0.1725, 0.0996]},
                {"start": [0.0, 0.1725, 0.0996], "end": [0.0, 0.165, 0.1122]},
                {"start": [0.0, 0.165, 0.1122], "end": [0.0, 0.1575, 0.1182]},
                {"start": [0.0, 0.1575, 0.1182], "end": [0.0, 0.15, 0.2]},
                {"start": [0.0, 0.15, 0.12], "end": [0.0, 0.1475, 0.1182]},
                {"start": [0.0, 0.1475, 0.1182], "end": [0.0, 0.135, 0.1122]},
                {"start": [0.0, 0.135, 0.1122], "end": [0.0, 0.1275, 0.0996]}
            ]
        },
        {
            "name": "ㅄ",
            "kind": ["son"],
            "path": [
                {"start": [0.0, 0.0, 0.2], "end": [0.0, 0.0, 0.0]},
                {"start": [0.0, 0.09, 0.2], "end": [0.0, 0.09, 0.0]},
                {"start": [0.0, 0.0, 0.1], "end": [0.0, 0.09, 0.1]},
                {"start": [0.0, 0.0, 0.0], "end": [0.0, 0.09, 0.0]},
                {"start": [0.0, 0.16, 0.2], "end": [0.0, 0.1, 0.0]},
                {"start": [0.0, 0.155, 0.17], "end": [0.0, 0.2, 0.0]}
            ]
        },
        {
            "name": "ㅏ",
            "kind": ["mom", 0],
            "path": [
                {"start": [0.0, 0.14, 0.2], "end": [0.0, 0.14, 0.0]},
                {"start": [0.0, 0.14, 0.1], "end": [0.0, 0.2, 0.1]}
            ]
        },
        {
            "name": "ㅑ",
            "kind": ["mom", 0],
            "path": [
                {"start": [0.0, 0.14, 0.2], "end": [0.0, 0.14, 0.0]},
                {"start": [0.0, 0.14, 0.13], "end": [0.0, 0.2, 0.13]},
                {"start": [0.0, 0.14, 0.07], "end": [0.0, 0.2, 0.07]}
            ]
        },
        {
            "name": "ㅓ",
            "kind": ["mom", 0],
            "path": [
                {"start": [0.0, 0.14, 0.1], "end": [0.0, 0.2, 0.1]},
                {"start": [0.0, 0.2, 0.2], "end": [0.0, 0.2, 0.0]}
            ]
        },
        {
            "name": "ㅕ",
            "kind": ["mom", 0],
            "path": [
                {"start": [0.0, 0.14, 0.13], "end": [0.0, 0.2, 0.13]},
                {"start": [0.0, 0.14, 0.07], "end": [0.0, 0.2, 0.07]},
                {"start": [0.0, 0.2, 0.2], "end": [0.0, 0.2, 0.0]}
            ]
        },
        {
            "name": "ㅗ",
            "kind": ["mom", 1],
            "path": [
                {"start": [0.0, 0.1, 0.05], "end": [0.0, 0.1, 0.0]},
                {"start": [0.0, 0.0, 0.0], "end": [0.0, 0.2, 0.0]}
            ]
        },
        {
            "name": "ㅛ",
            "kind": ["mom", 1],
            "path": [
                {"start": [0.0, 0.07, 0.05], "end": [0.0, 0.07, 0.0]},
                {"start": [0.0, 0.13, 0.05], "end": [0.0, 0.13, 0.0]},
                {"start": [0.0, 0.0, 0.0], "end": [0.0, 0.2, 0.0]}
            ]
        },
        {
            "name": "ㅜ",
            "kind": ["mom", 1],
            "path": [
                {"start": [0.0, 0.0, 0.05], "end": [0.0, 0.2, 0.05]},
                {"start": [0.0, 0.1, 0.05], "end": [0.0, 0.1, 0.0]}
            ]
        },
        {
            "name": "ㅠ",
            "kind": ["mom", 1],
            "path": [
                {"start": [0.0, 0.0, 0.05], "end": [0.0, 0.2, 0.05]},
                {"start": [0.0, 0.07, 0.05], "end": [0.0, 0.07, 0.0]},
                {"start": [0.0, 0.13, 0.05], "end": [0.0, 0.13, 0.0]}
            ]
        },
        {
            "name": "ㅡ",
            "kind": ["mom", 1],
            "path": [
                {"start": [0.0, 0.0, 0.02], "end": [0.0, 0.2, 0.02]}
            ]
        },
        {
            "name": "ㅣ",
            "kind": ["mom", 0],
            "path": [
                {"start": [0.0, 0.18, 0.2], "end": [0.0, 0.18, 0.0]}
            ]
        },
        {
            "name": "ㅢ",
            "kind": ["mom", 2],
            "path": [
                {"start": [0.0, 0.0, 0.05], "end": [0.0, 0.18, 0.05]},
                {"start": [0.0, 0.2, 0.2], "end": [0.0, 0.2, 0.0]}
            ]
        },
        {
            "name": "ㅚ",
            "kind": ["mom", 2],
            "path": [
                {"start": [0.0, 0.09, 0.1], "end": [0.0, 0.09, 0.02]},
                {"start": [0.0, 0.0, 0.02], "end": [0.0, 0.18, 0.02]},
                {"start": [0.0, 0.2, 0.2], "end": [0.0, 0.2, 0.0]}
            ]
        },
        {
            "name": "ㅐ",
            "kind": ["mom", 0],
            "path": [
                {"start": [0.0, 0.14, 0.19], "end": [0.0, 0.14, 0.01]},
                {"start": [0.0, 0.14, 0.1], "end": [0.0, 0.2, 0.1]},
                {"start": [0.0, 0.2, 0.2], "end": [0.0, 0.2, 0.0]}
            ]
        },
        {
            "name": "ㅟ",
            "kind": ["mom", 2],
            "path": [
                {"start": [0.0, 0.0, 0.09], "end": [0.0, 0.18, 0.09]},
                {"start": [0.0, 0.09, 0.09], "end": [0.0, 0.09, 0.0]},
                {"start": [0.0, 0.2, 0.2], "end": [0.0, 0.2, 0.0]}
            ]
        },
        {
            "name": "ㅔ",
            "kind": ["mom", 0],
            "path": [
                {"start": [0.0, 0.14, 0.1], "end": [0.0, 0.17, 0.1]},
                {"start": [0.0, 0.17, 0.19], "end": [0.0, 0.17, 0.01]},
                {"start": [0.0, 0.2, 0.2], "end": [0.0, 0.2, 0.0]}
            ]
        },
        {
            "name": "ㅒ",
            "kind": ["mom", 0],
            "path": [
                {"start": [0.0, 0.14, 0.19], "end": [0.0, 0.14, 0.01]},
                {"start": [0.0, 0.14, 0.13], "end": [0.0, 0.2, 0.13]},
                {"start": [0.0, 0.14, 0.07], "end": [0.0, 0.2, 0.07]},
                {"start": [0.0, 0.2, 0.2], "end": [0.0, 0.2, 0.0]}
            ]
        },
        {
            "name": "ㅖ",
            "kind": ["mom", 0],
            "path": [
                {"start": [0.0, 0.14, 0.13], "end": [0.0, 0.17, 0.13]},
                {"start": [0.0, 0.14, 0.07], "end": [0.0, 0.17, 0.07]},
                {"start": [0.0, 0.17, 0.19], "end": [0.0, 0.17, 0.01]},
                {"start": [0.0, 0.2, 0.2], "end": [0.0, 0.2, 0.0]}
            ]
        },
        {
            "name": "ㅘ",
            "kind": ["mom", 2],
            "path": [
                {"start": [0.0, 0.07, 0.1], "end": [0.0, 0.07, 0.02]},
                {"start": [0.0, 0.0, 0.02], "end": [0.0, 0.14, 0.02]},
                {"start": [0.0, 0.15, 0.2], "end": [0.0, 0.15, 0.0]},
                {"start": [0.0, 0.15, 0.1], "end": [0.0, 0.2, 0.1]}
            ]
        },
        {
            "name": "ㅝ",
            "kind": ["mom", 2],
            "path": [
                {"start": [0.0, 0.0, 0.09], "end": [0.0, 0.18, 0.09]},
                {"start": [0.0, 0.09, 0.09], "end": [0.0, 0.09, 0.0]},
                {"start": [0.0, 0.11, 0.05], "end": [0.0, 0.2, 0.05]},
                {"start": [0.0, 0.2, 0.2], "end": [0.0, 0.2, 0.0]}
            ]
        },
        {
            "name": "ㅙ",
            "kind": ["mom", 2],
            "path": [
                {"start": [0.0, 0.07, 0.1], "end": [0.0, 0.07, 0.02]},
                {"start": [0.0, 0.0, 0.02], "end": [0.0, 0.14, 0.02]},
                {"start": [0.0, 0.15, 0.19], "end": [0.0, 0.15, 0.01]},
                {"start": [0.0, 0.15, 0.1], "end": [0.0, 0.2, 0.1]},
                {"start": [0.0, 0.2, 0.2], "end": [0.0, 0.2, 0.0]}
            ]
        },
        {
            "name": "ㅞ",
            "kind": ["mom", 2],
            "path": [
                {"start": [0.0, 0.0, 0.09], "end": [0.0, 0.16, 0.09]},
                {"start": [0.0, 0.08, 0.09], "end": [0.0, 0.08, 0.0]},
                {"start": [0.0, 0.11, 0.05], "end": [0.0, 0.17, 0.05]},
                {"start": [0.0, 0.17, 0.19], "end": [0.0, 0.17, 0.01]},
                {"start": [0.0, 0.2, 0.2], "end": [0.0, 0.2, 0.0]}
            ]
        }
    ]
}